oraczenhq/__init__.py
oraczenhq/authorization/__init__.py
oraczenhq/authorization/lib.py
oraczenhq_authorization-0.0.3.dist-info/METADATA
oraczenhq_authorization-0.0.3.dist-info/WHEEL
oraczenhq_authorization-0.0.3.dist-info/top_level.txt
oraczenhq_authorization-0.0.3.dist-info/RECORD
