Metadata-Version: 2.4
Name: oraczenhq-authorization
Version: 0.0.3
Summary: Authorization client
Requires-Dist: redis<7.0.0,>=6.2.0
Requires-Dist: pydantic<3.0.0,>=2.11.0
Requires-Dist: openfga-sdk<1.0.0,>=0.9.4
Dynamic: description
Dynamic: description-content-type
Dynamic: requires-dist
Dynamic: summary
